pkg_try_19_mb/__init__.py
pkg_try_19_mb/preprocess.py
pkg_try_19_mb-0.0.1.dist-info/LICENSE.txt
pkg_try_19_mb-0.0.1.dist-info/METADATA
pkg_try_19_mb-0.0.1.dist-info/WHEEL
pkg_try_19_mb-0.0.1.dist-info/entry_points.txt
pkg_try_19_mb-0.0.1.dist-info/top_level.txt
pkg_try_19_mb-0.0.1.dist-info/RECORD
