Metadata-Version: 2.1
Name: pkg-try-19-mb
Version: 0.0.1
Summary: A basic hello package
Home-page: UNKNOWN
Author: Mehri
Author-email: mehri.baniasadi92@gmail.com
License: UNKNOWN
Keywords: python
Platform: UNKNOWN
Classifier: Development Status :: 1 - Planning
Classifier: Intended Audience :: Developers
Classifier: Programming Language :: Python :: 3
Classifier: Operating System :: Unix
Classifier: Operating System :: MacOS :: MacOS X
Classifier: Operating System :: Microsoft :: Windows
License-File: LICENSE.txt
Requires-Dist: numpy (==1.17.4)
Requires-Dist: nibabel (==2.5.1)
Requires-Dist: scipy (==1.3.1)
Requires-Dist: nnunet-inference-on-cpu-and-gpu (==1.6.6)
Requires-Dist: batchgenerators (==0.21)
